{
    "development": {
        "host": "localhost",
        "user": "root",
        "password": "",
        "database_name": "splite_sheet",
        "dialect": "mysql"
    },
    "test": {
        "host": "localhost",
        "user": "root",
        "password": "",
        "database_name": "splite_sheet",
        "dialect": "mysql"
    }, 
    "production": {
        "host": "localhost",
        "user": "root",
        "password": "",
        "database_name": "splite_sheet",
        "dialect": "mysql"
    }
}